readcraft/__init__.py
readcraft/readme_generator.py
readcraft-0.1.6.dist-info/LICENSE
readcraft-0.1.6.dist-info/METADATA
readcraft-0.1.6.dist-info/WHEEL
readcraft-0.1.6.dist-info/entry_points.txt
readcraft-0.1.6.dist-info/top_level.txt
readcraft-0.1.6.dist-info/RECORD
