Metadata-Version: 2.1
Name: readcraft
Version: 0.1.6
Summary: A command-line tool to generate README.md files using the Groq API.
Home-page: https://github.com/tasbi03/ReadCraft
Author: Tasbi Tasbi
Author-email: ttasbi@myseneca.ca
Classifier: Development Status :: 4 - Beta
Classifier: Intended Audience :: Developers
Classifier: Topic :: Software Development :: Documentation
Classifier: Programming Language :: Python :: 3.7
Classifier: Programming Language :: Python :: 3.8
Classifier: Programming Language :: Python :: 3.9
Classifier: Programming Language :: Python :: 3.10
Classifier: Programming Language :: Python :: 3.11
Classifier: Programming Language :: Python :: 3.12
Classifier: License :: OSI Approved :: MIT License
Classifier: Operating System :: OS Independent
Requires-Python: >=3.7
License-File: LICENSE
Requires-Dist: requests >=2.31.0
Requires-Dist: python-dotenv >=1.0.0
Requires-Dist: toml >=0.10.2
Provides-Extra: dev
Requires-Dist: pytest ; extra == 'dev'
Requires-Dist: flake8 ; extra == 'dev'
